vt/__init__.py
vt/client.py
vt/error.py
vt/feed.py
vt/iterator.py
vt/object.py
vt/utils.py
vt/version.py
vt_py-0.18.4.dist-info/METADATA
vt_py-0.18.4.dist-info/WHEEL
vt_py-0.18.4.dist-info/top_level.txt
vt_py-0.18.4.dist-info/RECORD
