Metadata-Version: 2.1
Name: vt-py
Version: 0.18.4
Summary: The official Python client library for VirusTotal
Home-page: https://github.com/VirusTotal/vt-py
License: Apache 2
Classifier: Programming Language :: Python :: 3
Classifier: License :: OSI Approved :: Apache Software License
Classifier: Operating System :: OS Independent
Requires-Python: >=3.7.0
Requires-Dist: aiohttp==3.8.6; python_version == "3.7"
Requires-Dist: aiohttp; python_version > "3.7"
Provides-Extra: test
Requires-Dist: pytest; extra == "test"
Requires-Dist: pytest_httpserver; extra == "test"
Requires-Dist: pytest_asyncio; extra == "test"
Requires-Dist: flask; extra == "test"
